simplechat/__init__.py
simplechat/cli.py
simplechat/db.py
simplechat/plugin.py
simplechat/settings.py
simplemind_chat-0.1.8.dist-info/LICENSE
simplemind_chat-0.1.8.dist-info/METADATA
simplemind_chat-0.1.8.dist-info/WHEEL
simplemind_chat-0.1.8.dist-info/entry_points.txt
simplemind_chat-0.1.8.dist-info/top_level.txt
simplemind_chat-0.1.8.dist-info/RECORD
