Metadata-Version: 2.1
Name: simplemind-chat
Version: 0.1.8
Summary: A chat interface for AI models using Simplemind.
Requires-Python: >=3.11
License-File: LICENSE
Requires-Dist: appdirs
Requires-Dist: docopt
Requires-Dist: rich
Requires-Dist: prompt-toolkit
Requires-Dist: xerox
Requires-Dist: simplemind[full]
Requires-Dist: spacy
Requires-Dist: nltk
